sparselm/__init__.py
sparselm/optimizer.py
sparselm/tools.py
sparselm/model/__init__.py
sparselm/model/_adaptive_lasso.py
sparselm/model/_base.py
sparselm/model/_lasso.py
sparselm/model/_ols.py
sparselm/model/miqp/__init__.py
sparselm/model/miqp/_best_subset.py
sparselm/model/miqp/_regularized_l0.py
sparse_lm-0.2.0.dist-info/LICENSE
sparse_lm-0.2.0.dist-info/METADATA
sparse_lm-0.2.0.dist-info/WHEEL
sparse_lm-0.2.0.dist-info/top_level.txt
sparse_lm-0.2.0.dist-info/RECORD
