Metadata-Version: 2.1
Name: sparse-lm
Version: 0.2.0
Summary: Sparse linear regression models
Author-email: Luis Barroso-Luque <lbluque@berkeley.edu>
License: BSD 3-Clause License
Classifier: Development Status :: 3 - Alpha
Classifier: Programming Language :: Python :: 3 :: Only
Classifier: Programming Language :: Python :: 3.8
Classifier: Programming Language :: Python :: 3.9
Classifier: Programming Language :: Python :: 3.10
Classifier: Intended Audience :: Science/Research
Classifier: License :: OSI Approved :: BSD License
Classifier: Operating System :: OS Independent
Classifier: Topic :: Scientific/Engineering :: Information Analysis
Classifier: Topic :: Scientific/Engineering :: Mathematics
Classifier: Topic :: Software Development :: Libraries :: Python Modules
License-File: LICENSE
Requires-Dist: numpy
Requires-Dist: cvxpy
Requires-Dist: scikit-learn
